<annotation verified="yes">
    <folder>Annotation</folder>
    <filename>adimg16.jpg</filename>
    <path>additional_can_images-PascalVOC-export/Annotations/adimg16.jpg</path>
    <source>
        <database>Unknown</database>
    </source>
    <size>
        <width>225</width>
        <height>225</height>
        <depth>3</depth>
    </size>
    <segmented>0</segmented>
    <object>
    <name>can</name>
    <pose>Unspecified</pose>
    <truncated>0</truncated>
    <difficult>0</difficult>
    <bndbox>
        <xmin>33.27814569536424</xmin>
        <ymin>32.28476821192053</ymin>
        <xmax>194.20529801324503</xmax>
        <ymax>192.2185430463576</ymax>
    </bndbox>
</object>
</annotation>
