<annotation verified="yes">
    <folder>Annotation</folder>
    <filename>can_img243.jpg</filename>
    <path>robo_images-PascalVOC-export/Annotations/can_img243.jpg</path>
    <source>
        <database>Unknown</database>
    </source>
    <size>
        <width>800</width>
        <height>600</height>
        <depth>3</depth>
    </size>
    <segmented>0</segmented>
    <object>
    <name>can</name>
    <pose>Unspecified</pose>
    <truncated>0</truncated>
    <difficult>0</difficult>
    <bndbox>
        <xmin>367.3728813559322</xmin>
        <ymin>73.22034674175714</ymin>
        <xmax>800</xmax>
        <ymax>522.0338983050847</ymax>
    </bndbox>
</object>
</annotation>
