<annotation verified="yes">
    <folder>Annotation</folder>
    <filename>img138.jpg</filename>
    <path>robo_images-PascalVOC-export/Annotations/img138.jpg</path>
    <source>
        <database>Unknown</database>
    </source>
    <size>
        <width>600</width>
        <height>450</height>
        <depth>3</depth>
    </size>
    <segmented>0</segmented>
    <object>
    <name>can</name>
    <pose>Unspecified</pose>
    <truncated>0</truncated>
    <difficult>0</difficult>
    <bndbox>
        <xmin>38.32628282450013</xmin>
        <ymin>2.0339012145996094</ymin>
        <xmax>571.7161016949152</xmax>
        <ymax>446.4406934835143</ymax>
    </bndbox>
</object>
</annotation>
